smqtk_dataprovider/__init__.py
smqtk_dataprovider/content_type_validator.py
smqtk_dataprovider/exceptions.py
smqtk_dataprovider/impls/__init__.py
smqtk_dataprovider/impls/data_element/__init__.py
smqtk_dataprovider/impls/data_element/file.py
smqtk_dataprovider/impls/data_element/girder.py
smqtk_dataprovider/impls/data_element/hbase.py
smqtk_dataprovider/impls/data_element/matrix.py
smqtk_dataprovider/impls/data_element/memory.py
smqtk_dataprovider/impls/data_element/psql.py
smqtk_dataprovider/impls/data_element/url.py
smqtk_dataprovider/impls/data_set/__init__.py
smqtk_dataprovider/impls/data_set/file.py
smqtk_dataprovider/impls/data_set/kvstore_backed.py
smqtk_dataprovider/impls/data_set/memory.py
smqtk_dataprovider/impls/data_set/psql.py
smqtk_dataprovider/impls/key_value_store/__init__.py
smqtk_dataprovider/impls/key_value_store/memory.py
smqtk_dataprovider/impls/key_value_store/postgres.py
smqtk_dataprovider/interfaces/__init__.py
smqtk_dataprovider/interfaces/data_element.py
smqtk_dataprovider/interfaces/data_set.py
smqtk_dataprovider/interfaces/key_value_store.py
smqtk_dataprovider/py.typed
smqtk_dataprovider/utils/__init__.py
smqtk_dataprovider/utils/file.py
smqtk_dataprovider/utils/postgres.py
smqtk_dataprovider/utils/simple_timer.py
smqtk_dataprovider/utils/string.py
smqtk_dataprovider-0.19.0.dist-info/LICENSE.txt
smqtk_dataprovider-0.19.0.dist-info/METADATA
smqtk_dataprovider-0.19.0.dist-info/WHEEL
smqtk_dataprovider-0.19.0.dist-info/entry_points.txt
smqtk_dataprovider-0.19.0.dist-info/RECORD
