Metadata-Version: 2.1
Name: smqtk_dataprovider
Version: 0.19.0
Summary: SMQTK Data provision abstractions and implementations
Home-page: https://github.com/Kitware/SMQTK-Dataprovider
License: BSD-3-Clause
Author: Kitware, Inc.
Author-email: smqtk-developers@kitware.com
Requires-Python: >=3.10,<4.0
Classifier: Development Status :: 3 - Alpha
Classifier: Intended Audience :: Developers
Classifier: Intended Audience :: Science/Research
Classifier: License :: OSI Approved :: BSD License
Classifier: Operating System :: MacOS :: MacOS X
Classifier: Operating System :: Unix
Classifier: Programming Language :: Python :: 3
Classifier: Programming Language :: Python :: 3.10
Classifier: Programming Language :: Python :: 3.11
Classifier: Programming Language :: Python :: 3.12
Classifier: Programming Language :: Python :: 3.13
Provides-Extra: filemagic
Provides-Extra: girder
Provides-Extra: psql
Requires-Dist: file-magic (>=0.4.0) ; extra == "filemagic"
Requires-Dist: girder-client (>=3.1.3) ; extra == "girder"
Requires-Dist: numpy (>=1.23.5,<2.0) ; python_version < "3.13"
Requires-Dist: numpy (>=2.1) ; python_version >= "3.13"
Requires-Dist: psycopg2-binary (>=2.9.10) ; extra == "psql"
Requires-Dist: requests (>=2.28.1)
Requires-Dist: smqtk-core (>=0.20)
Project-URL: Documentation, https://smqtk-dataprovider.readthedocs.io/
Project-URL: Repository, https://github.com/Kitware/SMQTK-Dataprovider
